odoo/addons/account_financial_report/README.rst
odoo/addons/account_financial_report/__init__.py
odoo/addons/account_financial_report/__manifest__.py
odoo/addons/account_financial_report/menuitems.xml
odoo/addons/account_financial_report/reports.xml
odoo/addons/account_financial_report/i18n/account_financial_report.pot
odoo/addons/account_financial_report/i18n/ar.po
odoo/addons/account_financial_report/i18n/ca.po
odoo/addons/account_financial_report/i18n/de.po
odoo/addons/account_financial_report/i18n/es.po
odoo/addons/account_financial_report/i18n/es_AR.po
odoo/addons/account_financial_report/i18n/es_MX.po
odoo/addons/account_financial_report/i18n/fi.po
odoo/addons/account_financial_report/i18n/fr.po
odoo/addons/account_financial_report/i18n/fr_CH.po
odoo/addons/account_financial_report/i18n/fr_FR.po
odoo/addons/account_financial_report/i18n/hr.po
odoo/addons/account_financial_report/i18n/hr_HR.po
odoo/addons/account_financial_report/i18n/it.po
odoo/addons/account_financial_report/i18n/ja.po
odoo/addons/account_financial_report/i18n/nl.po
odoo/addons/account_financial_report/i18n/nl_NL.po
odoo/addons/account_financial_report/i18n/pt.po
odoo/addons/account_financial_report/i18n/pt_BR.po
odoo/addons/account_financial_report/i18n/ro.po
odoo/addons/account_financial_report/i18n/sl.po
odoo/addons/account_financial_report/i18n/sv.po
odoo/addons/account_financial_report/i18n/sv_SE.po
odoo/addons/account_financial_report/models/__init__.py
odoo/addons/account_financial_report/models/account.py
odoo/addons/account_financial_report/models/account_group.py
odoo/addons/account_financial_report/models/account_move_line.py
odoo/addons/account_financial_report/models/ir_actions_report.py
odoo/addons/account_financial_report/readme/CONTRIBUTORS.rst
odoo/addons/account_financial_report/readme/DESCRIPTION.rst
odoo/addons/account_financial_report/readme/HISTORY.rst
odoo/addons/account_financial_report/readme/ROADMAP.rst
odoo/addons/account_financial_report/report/__init__.py
odoo14_addon_account_financial_report-14.0.3.14.2.dist-info/METADATA
odoo14_addon_account_financial_report-14.0.3.14.2.dist-info/WHEEL
odoo14_addon_account_financial_report-14.0.3.14.2.dist-info/top_level.txt
odoo14_addon_account_financial_report-14.0.3.14.2.dist-info/RECORD
