Metadata-Version: 2.1
Name: odoo14-addon-account_financial_report
Version: 14.0.3.14.2
Summary: OCA Financial Reports
Home-page: https://github.com/OCA/account-financial-reporting
Author: Camptocamp,initOS GmbH,redCOR AG,ForgeFlow,Odoo Community Association (OCA)
Author-email: support@odoo-community.org
License: AGPL-3
Classifier: Programming Language :: Python
Classifier: Framework :: Odoo
Classifier: Framework :: Odoo :: 14.0
Classifier: License :: OSI Approved :: GNU Affero General Public License v3
Requires-Python: >=3.6
Requires-Dist: odoo14-addon-date-range
Requires-Dist: odoo14-addon-report-xlsx
Requires-Dist: odoo<14.1dev,>=14.0a
